pykinematics/__init__.py
pykinematics/common.py
pykinematics/core.py
pykinematics/version.py
pykinematics/imu/__init__.py
pykinematics/imu/utility.py
pykinematics/imu/lib/__init__.py
pykinematics/imu/lib/angles.py
pykinematics/imu/lib/calibration.py
pykinematics/imu/lib/joints.py
pykinematics/imu/optimize/__init__.py
pykinematics/imu/optimize/filters.py
pykinematics/imu/orientation/__init__.py
pykinematics/imu/orientation/orientation.py
pykinematics/omc/__init__.py
pykinematics/omc/angles.py
pykinematics/omc/calibration.py
pykinematics/omc/segmentFrames.py
pykinematics/omc/utility.py
pykinematics/tests/__init__.py
pykinematics/tests/__main__.py
pykinematics/tests/conftest.py
pykinematics/tests/test_common.py
pykinematics/tests/test_imports.py
pykinematics-1.0.1.dist-info/LICENSE
pykinematics-1.0.1.dist-info/METADATA
pykinematics-1.0.1.dist-info/WHEEL
pykinematics-1.0.1.dist-info/top_level.txt
pykinematics-1.0.1.dist-info/RECORD
