Metadata-Version: 2.1
Name: pykinematics
Version: 1.0.1
Summary: Calculation of hip joint angles from wearable inertial sensors and optical motion capture.
Home-page: https://github.com/M-SenseResearchGroup/pymotion
Author: Lukas Adamowicz
Author-email: lukas.adamowicz95@gmail.com
License: MIT
Project-URL: Documentation, https://pykinematics.readthedocs.io/en/latest/
Platform: UNKNOWN
Classifier: Programming Language :: Python :: 3
Classifier: License :: OSI Approved :: MIT License
Classifier: Operating System :: OS Independent
Classifier: Topic :: Scientific/Engineering
Classifier: Programming Language :: Python :: 3.7
Requires-Python: >=3.6
